IiliIo/IiliIo.py
IiliIo/__init__.py
IiliIo-1.0.3.dist-info/LICENSE
IiliIo-1.0.3.dist-info/METADATA
IiliIo-1.0.3.dist-info/WHEEL
IiliIo-1.0.3.dist-info/entry_points.txt
IiliIo-1.0.3.dist-info/top_level.txt
IiliIo-1.0.3.dist-info/RECORD
