Metadata-Version: 2.1
Name: IiliIo
Version: 1.0.3
Summary: IiliIo uploader without API key
Home-page: https://github.com/OneFinalHug/IiliIo/
Author: OneFinalHug
Author-email: voidlillis@gmail.com
License: MIT
Keywords: IiliIo_uploader,telegram,host,uploader,IiliIo,image
Classifier: Programming Language :: Python :: 3.9
Classifier: License :: OSI Approved :: MIT License
Classifier: Operating System :: OS Independent
License-File: LICENSE
Requires-Dist: requests
Requires-Dist: colorclip
Requires-Dist: fake-useragent
Requires-Dist: requests-toolbelt
